{"version":2,"kind":"Notebook","sha256":"c58f5f8e7afb28fccd15c5eb8b24f1d58837427742da5232a12623cfe536e8ea","slug":"stack-dask-101","location":"/STACK/STACK-Dask-101.ipynb","dependencies":[],"frontmatter":{"title":"STACK service - Dask 101","content_includes_title":true,"kernelspec":{"name":"python_dedl","display_name":"Python DEDL","language":"python"},"numbering":{"title":{"offset":2}},"thumbnail":"/build/b27bd30f978ddf0848f3ea0942070886.jpeg","exports":[{"format":"ipynb","filename":"STACK-Dask-101.ipynb","url":"/build/STACK-Dask-101-5b268b820cbc5220884dc0b8fcb48e39.ipynb"}]},"widgets":{},"mdast":{"type":"root","children":[{"type":"block","kind":"notebook-content","children":[{"type":"image","url":"/build/b27bd30f978ddf0848f3ea0942070886.jpeg","position":{"start":{"line":1,"column":1},"end":{"line":1,"column":1}},"key":"Rnlv4kICyk","urlSource":"https://github.com/destination-earth/DestinE-DataLake-Lab/blob/main/img/DestinE-banner.jpg?raw=true"}],"key":"ngKY8zGpaH"},{"type":"block","kind":"notebook-content","children":[{"type":"paragraph","position":{"start":{"line":1,"column":1},"end":{"line":1,"column":1}},"children":[{"type":"strong","position":{"start":{"line":1,"column":1},"end":{"line":1,"column":1}},"children":[{"type":"text","value":"Licence","position":{"start":{"line":1,"column":1},"end":{"line":1,"column":1}},"key":"I0OP2qqVPv"}],"key":"B17AsmZE38"},{"type":"text","value":": MIT ","position":{"start":{"line":1,"column":1},"end":{"line":1,"column":1}},"key":"VZaQpUe8ld"},{"type":"break","key":"gCUbWQ9ddM"}],"key":"l4yEPRnfQV"},{"type":"image","url":"/build/2b00998ddd74a039529882b6d26ca076.svg","alt":"Dask logo","key":"bTFZaZWu18","urlSource":"https://docs.dask.org/en/latest/_images/dask_horizontal.svg"},{"type":"heading","depth":1,"position":{"start":{"line":5,"column":1},"end":{"line":5,"column":1}},"children":[{"type":"text","value":"STACK service - Dask 101","position":{"start":{"line":5,"column":1},"end":{"line":5,"column":1}},"key":"zMmPzOZSWo"}],"identifier":"stack-service-dask-101","label":"STACK service - Dask 101","html_id":"stack-service-dask-101","implicit":true,"key":"irNE93vbwT"},{"type":"div","class":"alert-info","children":[{"type":"heading","depth":4,"children":[{"type":"text","value":"Overview","key":"bgz5h51VDc"}],"identifier":"overview","label":"Overview","html_id":"overview","implicit":true,"key":"BkqSm23Mad"},{"type":"heading","depth":5,"children":[{"type":"text","value":"Content","key":"f8NMVDM2Kt"}],"identifier":"content","label":"Content","html_id":"content","implicit":true,"key":"tSFC4y3IWa"},{"type":"listItem","spread":false,"checked":null,"children":[{"type":"paragraph","children":[{"type":"text","value":"Dask API introduction","key":"wJeSKWZxZc"}],"key":"FAhGBGNObf"}],"key":"XRiEdvpfdc"},{"type":"listItem","spread":false,"checked":null,"children":[{"type":"paragraph","children":[{"type":"text","value":"dask.distributed","key":"nrULEXZXRE"}],"key":"Gfkt0uQn5O"}],"key":"usIyWZtbjm"},{"type":"listItem","spread":false,"checked":null,"children":[{"type":"paragraph","children":[{"type":"text","value":"DestinE DataLake Dask Cluster","key":"H79TjwJApN"}],"key":"JeuPT6GYtG"}],"key":"X71BoUEp9w"},{"type":"heading","depth":5,"children":[{"type":"text","value":"Duration: 20 min.","key":"gQk53Ujg0k"}],"identifier":"duration-20-min","label":"Duration: 20 min.","html_id":"duration-20-min","implicit":true,"key":"kLeteC4ocm"}],"key":"O0YX1XrVbA"},{"type":"break","key":"QGdicbq5NL"},{"type":"div","class":"alert-warning","children":[{"type":"text","value":"Please make sure Python DEDL kernel is used, and run the mamba install command.","key":"eyvFIxJGjh"}],"key":"x0GMeWi4fu"},{"type":"heading","depth":2,"position":{"start":{"line":21,"column":1},"end":{"line":21,"column":1}},"children":[{"type":"text","value":"What is ","position":{"start":{"line":21,"column":1},"end":{"line":21,"column":1}},"key":"w6Vw9WD74D"},{"type":"link","url":"%22https://www.dask.org/%22","position":{"start":{"line":21,"column":1},"end":{"line":21,"column":1}},"children":[{"type":"text","value":"Dask","position":{"start":{"line":21,"column":1},"end":{"line":21,"column":1}},"key":"i9W1ondDNq"}],"urlSource":"%22https://www.dask.org/%22","key":"kNcItW7Ekb"},{"type":"text","value":"?","position":{"start":{"line":21,"column":1},"end":{"line":21,"column":1}},"key":"Jrqt02dtPQ"}],"identifier":"what-is-dask","label":"What is Dask?","html_id":"what-is-dask","implicit":true,"key":"ce4huTQBiN"},{"type":"paragraph","position":{"start":{"line":22,"column":1},"end":{"line":22,"column":1}},"children":[{"type":"text","value":"Dask is a Python library for parallel and distributed computing.","position":{"start":{"line":22,"column":1},"end":{"line":22,"column":1}},"key":"vAhv6T9eGN"}],"key":"NBfon8uOpQ"},{"type":"paragraph","position":{"start":{"line":24,"column":1},"end":{"line":24,"column":1}},"children":[{"type":"text","value":"Dask addresses the challenge of scaling Python code from a single machine to large clusters of machines. In the world of data science and scientific computing, Python is a popular language due to its ease of use and extensive libraries like NumPy, Pandas, and scikit-learn. However, these libraries often struggle to handle large datasets that exceed the memory capacity of a single machine or require parallel processing for efficient computation.","position":{"start":{"line":24,"column":1},"end":{"line":24,"column":1}},"key":"hrLthe0wxR"}],"key":"pYWoWMheF8"},{"type":"paragraph","position":{"start":{"line":26,"column":1},"end":{"line":26,"column":1}},"children":[{"type":"text","value":"Dask provides parallel computing capabilities and allows Python developers to work with larger-than-memory datasets by parallelizing computation across multiple cores within a single machine or distributing it across a cluster of machines. It achieves this by providing parallelized versions of familiar data structures like arrays, dataframes, and lists, which seamlessly integrate with existing Python code.","position":{"start":{"line":26,"column":1},"end":{"line":26,"column":1}},"key":"h4DtKSoYCf"}],"key":"tyUrRjeQtU"},{"type":"paragraph","position":{"start":{"line":28,"column":1},"end":{"line":28,"column":1}},"children":[{"type":"text","value":"Dask can run on your laptop or can be scaled out to full capacity to a cloud cluster or HPC system.","position":{"start":{"line":28,"column":1},"end":{"line":28,"column":1}},"key":"W19rkSmErU"}],"key":"e3ts8P1dAg"},{"type":"paragraph","position":{"start":{"line":30,"column":1},"end":{"line":30,"column":1}},"children":[{"type":"text","value":"It offeres a rich ecosystem of Python libraries to support use cases in multiple domains such as:","position":{"start":{"line":30,"column":1},"end":{"line":30,"column":1}},"key":"GfKafglKxU"}],"key":"R1XAOcKEr3"},{"type":"list","ordered":false,"spread":false,"position":{"start":{"line":31,"column":1},"end":{"line":36,"column":1}},"children":[{"type":"listItem","spread":true,"position":{"start":{"line":31,"column":1},"end":{"line":31,"column":1}},"children":[{"type":"text","value":"Geospatial","position":{"start":{"line":31,"column":1},"end":{"line":31,"column":1}},"key":"uofDDXT3O5"}],"key":"LeojEnESwK"},{"type":"listItem","spread":true,"position":{"start":{"line":32,"column":1},"end":{"line":32,"column":1}},"children":[{"type":"text","value":"Finance","position":{"start":{"line":32,"column":1},"end":{"line":32,"column":1}},"key":"e9zCoKZIAT"}],"key":"xeaLM9UbCl"},{"type":"listItem","spread":true,"position":{"start":{"line":33,"column":1},"end":{"line":33,"column":1}},"children":[{"type":"text","value":"Astrophysics","position":{"start":{"line":33,"column":1},"end":{"line":33,"column":1}},"key":"I49wLadfkG"}],"key":"JpQn8Ur1r5"},{"type":"listItem","spread":true,"position":{"start":{"line":34,"column":1},"end":{"line":34,"column":1}},"children":[{"type":"text","value":"Microbiology","position":{"start":{"line":34,"column":1},"end":{"line":34,"column":1}},"key":"savgD0e8Jr"}],"key":"U4gXhrcsdt"},{"type":"listItem","spread":true,"position":{"start":{"line":35,"column":1},"end":{"line":36,"column":1}},"children":[{"type":"text","value":"Environmental science","position":{"start":{"line":35,"column":1},"end":{"line":35,"column":1}},"key":"EnFZ6XrjWZ"}],"key":"HDSdZ5cydS"}],"key":"qWfi8Umr5C"},{"type":"paragraph","position":{"start":{"line":37,"column":1},"end":{"line":37,"column":1}},"children":[{"type":"text","value":"Check out the Dask ","position":{"start":{"line":37,"column":1},"end":{"line":37,"column":1}},"key":"mtuRrmKY3n"},{"type":"link","url":"https://stories.dask.org/en/latest/","position":{"start":{"line":37,"column":1},"end":{"line":37,"column":1}},"children":[{"type":"text","value":"use cases","position":{"start":{"line":37,"column":1},"end":{"line":37,"column":1}},"key":"OYsafFhP93"}],"urlSource":"https://stories.dask.org/en/latest/","key":"b1r8Pelv7D"},{"type":"text","value":" page that provides a number of sample workflows to see how others are using Dask to solve their problems.","position":{"start":{"line":37,"column":1},"end":{"line":37,"column":1}},"key":"BjrjyyyRZu"}],"key":"T7u61u0Wmr"},{"type":"image","style":{"marginRight":"10px"},"url":"/build/undefined","alt":"Pangeologo","key":"CBgY7AlKvZ","urlSource":"https://global.discourse-cdn.com/standard14/uploads/pangeo/original/1X/657e3c5e0885ee4e5c2062c58f9aa094fa4b14a4.png"},{"type":"paragraph","position":{"start":{"line":41,"column":1},"end":{"line":41,"column":1}},"children":[{"type":"text","value":"Escpecially the ","position":{"start":{"line":41,"column":1},"end":{"line":41,"column":1}},"key":"DthaJS5fjS"},{"type":"link","url":"https://pangeo.io/index.html","position":{"start":{"line":41,"column":1},"end":{"line":41,"column":1}},"children":[{"type":"text","value":"Pangeo","position":{"start":{"line":41,"column":1},"end":{"line":41,"column":1}},"key":"bhdJggiopu"}],"urlSource":"https://pangeo.io/index.html","key":"JZqQuKo3mE"},{"type":"text","value":" community, a community of people working to enable big data geoscience, heavily relies on Dask as the core compute frameworks to be used. Why? Pangeo community early realised the need for scaleable software and tools to handle petabyte-scale datasets on HPC and cloud platforms.","position":{"start":{"line":41,"column":1},"end":{"line":41,"column":1}},"key":"OKSoVkzaYs"}],"key":"rs8erDtJyz"},{"type":"paragraph","position":{"start":{"line":43,"column":1},"end":{"line":43,"column":1}},"children":[{"type":"text","value":"Dask provides ","position":{"start":{"line":43,"column":1},"end":{"line":43,"column":1}},"key":"M54fae7jFZ"},{"type":"strong","position":{"start":{"line":43,"column":1},"end":{"line":43,"column":1}},"children":[{"type":"text","value":"multi-core","position":{"start":{"line":43,"column":1},"end":{"line":43,"column":1}},"key":"sahZ4bPLVh"}],"key":"qpArrX7034"},{"type":"text","value":" and ","position":{"start":{"line":43,"column":1},"end":{"line":43,"column":1}},"key":"v9vRR8Obyi"},{"type":"strong","position":{"start":{"line":43,"column":1},"end":{"line":43,"column":1}},"children":[{"type":"text","value":"distributed+parallel","position":{"start":{"line":43,"column":1},"end":{"line":43,"column":1}},"key":"m5S0TfUzUb"}],"key":"gP962awMVe"},{"type":"text","value":" execution on ","position":{"start":{"line":43,"column":1},"end":{"line":43,"column":1}},"key":"p9B3dOCIF5"},{"type":"strong","position":{"start":{"line":43,"column":1},"end":{"line":43,"column":1}},"children":[{"type":"text","value":"larger-than-memory","position":{"start":{"line":43,"column":1},"end":{"line":43,"column":1}},"key":"TLJd5F7ssF"}],"key":"y0mSRLrdZN"},{"type":"text","value":" datasets","position":{"start":{"line":43,"column":1},"end":{"line":43,"column":1}},"key":"OmMmuVzqVQ"}],"key":"nI7CKSC6Ak"},{"type":"heading","depth":3,"position":{"start":{"line":45,"column":1},"end":{"line":45,"column":1}},"children":[{"type":"text","value":"References","position":{"start":{"line":45,"column":1},"end":{"line":45,"column":1}},"key":"yqMPWojC76"}],"identifier":"references","label":"References","html_id":"references","implicit":true,"key":"V2QOm9363V"},{"type":"paragraph","position":{"start":{"line":47,"column":1},"end":{"line":47,"column":1}},"children":[{"type":"text","value":"This tutorial builds upon the following reference documents supported and maintained by the Dask and Pangeo communities.","position":{"start":{"line":47,"column":1},"end":{"line":47,"column":1}},"key":"EYeMkGrqSM"}],"key":"NCDhnNaDe9"},{"type":"list","ordered":false,"spread":false,"position":{"start":{"line":48,"column":1},"end":{"line":51,"column":1}},"children":[{"type":"listItem","spread":true,"position":{"start":{"line":48,"column":1},"end":{"line":48,"column":1}},"children":[{"type":"link","url":"https://tutorial.dask.org/","position":{"start":{"line":48,"column":1},"end":{"line":48,"column":1}},"children":[{"type":"text","value":"Dask Tutorial","position":{"start":{"line":48,"column":1},"end":{"line":48,"column":1}},"key":"SMB5mGPYHv"}],"urlSource":"https://tutorial.dask.org/","key":"OKSkeYtM9z"}],"key":"VCvqsVXE59"},{"type":"listItem","spread":true,"position":{"start":{"line":49,"column":1},"end":{"line":49,"column":1}},"children":[{"type":"link","url":"https://examples.dask.org/index.html","position":{"start":{"line":49,"column":1},"end":{"line":49,"column":1}},"children":[{"type":"text","value":"Dask Examples","position":{"start":{"line":49,"column":1},"end":{"line":49,"column":1}},"key":"t7nOiGDTp3"}],"urlSource":"https://examples.dask.org/index.html","key":"ZMWrjSwPDi"}],"key":"APUUu7EMz6"},{"type":"listItem","spread":true,"position":{"start":{"line":50,"column":1},"end":{"line":51,"column":1}},"children":[{"type":"link","url":"https://github.com/pangeo-data/pangeo-tutorial","position":{"start":{"line":50,"column":1},"end":{"line":50,"column":1}},"children":[{"type":"text","value":"Pangeo Tutorials","position":{"start":{"line":50,"column":1},"end":{"line":50,"column":1}},"key":"TBvrRbByQo"}],"urlSource":"https://github.com/pangeo-data/pangeo-tutorial","error":true,"key":"omjnBzjp9y"}],"key":"OPONtyuY0r"}],"key":"Hu66lF08FE"}],"key":"UktDee8QXU"},{"type":"block","kind":"notebook-content","children":[{"type":"heading","depth":2,"position":{"start":{"line":1,"column":1},"end":{"line":1,"column":1}},"children":[{"type":"text","value":"Dask Core Library (APIs)","position":{"start":{"line":1,"column":1},"end":{"line":1,"column":1}},"key":"ECfnDuIt8L"}],"identifier":"dask-core-library-apis","label":"Dask Core Library (APIs)","html_id":"dask-core-library-apis","implicit":true,"key":"lz4RBIJD9b"},{"type":"paragraph","position":{"start":{"line":2,"column":1},"end":{"line":3,"column":1}},"children":[{"type":"text","value":"Dask provides several APIs, also called collections, to enable distributed+parallel execution on larger-than-memory datasets.\nWe can think of Dask’s APIs at a high and a low level:","position":{"start":{"line":2,"column":1},"end":{"line":2,"column":1}},"key":"ONXoqXHh8e"}],"key":"LexWaIyLLa"},{"type":"paragraph","children":[{"type":"image","url":"/build/58d59d37a749bf97727f9be46ef12be2.png","alt":"High vs Low level clothes analogy","key":"PwSZytTYBW","urlSource":"https://tutorial.dask.org/_images/high_vs_low_level_coll_analogy.png"}],"key":"qroZKFkYtd"},{"type":"list","ordered":false,"spread":false,"position":{"start":{"line":9,"column":1},"end":{"line":14,"column":1}},"children":[{"type":"listItem","spread":true,"position":{"start":{"line":9,"column":1},"end":{"line":11,"column":1}},"children":[{"type":"strong","position":{"start":{"line":9,"column":1},"end":{"line":9,"column":1}},"children":[{"type":"text","value":"High-level collections:","position":{"start":{"line":9,"column":1},"end":{"line":9,"column":1}},"key":"OdmOa1hEpN"}],"key":"Bw7tcUIsAG"},{"type":"text","value":"  Dask provides high-level ","position":{"start":{"line":9,"column":1},"end":{"line":9,"column":1}},"key":"DHXjXv3bxX"},{"type":"strong","position":{"start":{"line":9,"column":1},"end":{"line":9,"column":1}},"children":[{"type":"text","value":"Array, Bag, and DataFrame","position":{"start":{"line":9,"column":1},"end":{"line":9,"column":1}},"key":"T47Ni9FSDO"}],"key":"GlhgCTcpe6"},{"type":"text","value":"\ncollections that mimic NumPy, lists, and pandas but can operate in parallel on\ndatasets that don’t fit into memory.","position":{"start":{"line":9,"column":1},"end":{"line":9,"column":1}},"key":"HbqJW2T9Ce"}],"key":"avaDSIKA3R"},{"type":"listItem","spread":true,"position":{"start":{"line":12,"column":1},"end":{"line":14,"column":1}},"children":[{"type":"strong","position":{"start":{"line":12,"column":1},"end":{"line":12,"column":1}},"children":[{"type":"text","value":"Low-level collections:","position":{"start":{"line":12,"column":1},"end":{"line":12,"column":1}},"key":"pZ8dQ3V4us"}],"key":"tBux0ofZMS"},{"type":"text","value":"  Dask also provides low-level ","position":{"start":{"line":12,"column":1},"end":{"line":12,"column":1}},"key":"G7bJrzzlCa"},{"type":"strong","position":{"start":{"line":12,"column":1},"end":{"line":12,"column":1}},"children":[{"type":"text","value":"Tasks (Delayed and Futures)","position":{"start":{"line":12,"column":1},"end":{"line":12,"column":1}},"key":"bAhlq4iagZ"}],"key":"BglUXYBdTu"},{"type":"text","value":"\ncollections that give you finer control to build custom parallel and distributed computations.","position":{"start":{"line":12,"column":1},"end":{"line":12,"column":1}},"key":"jaD3EkSDCi"}],"key":"ldFyupUYa3"}],"key":"gcv63E01pe"},{"type":"paragraph","position":{"start":{"line":15,"column":1},"end":{"line":15,"column":1}},"children":[{"type":"strong","position":{"start":{"line":15,"column":1},"end":{"line":15,"column":1}},"children":[{"type":"text","value":"In this tutorial we will focus on Dask Arrays and Tasks (Delayed and Futures). Please visit the ","position":{"start":{"line":15,"column":1},"end":{"line":15,"column":1}},"key":"QMozJLBvjh"},{"type":"link","url":"https://examples.dask.org/index.html","position":{"start":{"line":15,"column":1},"end":{"line":15,"column":1}},"children":[{"type":"text","value":"Dask Examples","position":{"start":{"line":15,"column":1},"end":{"line":15,"column":1}},"key":"GJju4fbGoT"}],"urlSource":"https://examples.dask.org/index.html","key":"rkPvkxR6YZ"},{"type":"text","value":" and ","position":{"start":{"line":15,"column":1},"end":{"line":15,"column":1}},"key":"CT1i4BTUW3"},{"type":"link","url":"https://tutorial.dask.org/","position":{"start":{"line":15,"column":1},"end":{"line":15,"column":1}},"children":[{"type":"text","value":"Dask Tutorial","position":{"start":{"line":15,"column":1},"end":{"line":15,"column":1}},"key":"pt8CNjcjrt"}],"urlSource":"https://tutorial.dask.org/","key":"La5jy3Vyhc"},{"type":"text","value":" for additional information.","position":{"start":{"line":15,"column":1},"end":{"line":15,"column":1}},"key":"Jj3xRU88qn"}],"key":"dZtxRfO2ZX"}],"key":"EXHyLNLqOT"}],"key":"iVFli2ksTw"},{"type":"block","kind":"notebook-content","children":[{"type":"heading","depth":3,"position":{"start":{"line":1,"column":1},"end":{"line":1,"column":1}},"children":[{"type":"text","value":"dask.array - parallelized numpy","position":{"start":{"line":1,"column":1},"end":{"line":1,"column":1}},"key":"ZFPNd6MrPS"}],"identifier":"dask-array-parallelized-numpy","label":"dask.array - parallelized numpy","html_id":"dask-array-parallelized-numpy","implicit":true,"key":"m1uS48hWPA"},{"type":"paragraph","position":{"start":{"line":3,"column":1},"end":{"line":3,"column":1}},"children":[{"type":"text","value":"Parallel, larger-than-memory, n-dimensional array using blocked algorithms.","position":{"start":{"line":3,"column":1},"end":{"line":3,"column":1}},"key":"uZ3t1b2rKx"}],"key":"FGSXOSZGhq"},{"type":"list","ordered":false,"spread":false,"position":{"start":{"line":5,"column":1},"end":{"line":7,"column":1}},"children":[{"type":"listItem","spread":true,"position":{"start":{"line":5,"column":1},"end":{"line":5,"column":1}},"children":[{"type":"strong","position":{"start":{"line":5,"column":1},"end":{"line":5,"column":1}},"children":[{"type":"text","value":"Parallel","position":{"start":{"line":5,"column":1},"end":{"line":5,"column":1}},"key":"zDf3PcXbwx"}],"key":"WfnKsq7RFL"},{"type":"text","value":": Uses all of the cores on your computer","position":{"start":{"line":5,"column":1},"end":{"line":5,"column":1}},"key":"LVQYOrtRGs"}],"key":"sww1h61kAP"},{"type":"listItem","spread":true,"position":{"start":{"line":6,"column":1},"end":{"line":6,"column":1}},"children":[{"type":"strong","position":{"start":{"line":6,"column":1},"end":{"line":6,"column":1}},"children":[{"type":"text","value":"Larger-than-memory","position":{"start":{"line":6,"column":1},"end":{"line":6,"column":1}},"key":"tcA5UbpHHf"}],"key":"cJjOVzEyrC"},{"type":"text","value":":  Lets you work on datasets that are larger than your available memory by breaking up your array into many small pieces, operating on those pieces in an order that minimizes the memory footprint of your computation, and effectively streaming data from disk.","position":{"start":{"line":6,"column":1},"end":{"line":6,"column":1}},"key":"vhQrmefx8w"}],"key":"wJDl7A9u3d"},{"type":"listItem","spread":true,"position":{"start":{"line":7,"column":1},"end":{"line":7,"column":1}},"children":[{"type":"strong","position":{"start":{"line":7,"column":1},"end":{"line":7,"column":1}},"children":[{"type":"text","value":"Blocked Algorithms","position":{"start":{"line":7,"column":1},"end":{"line":7,"column":1}},"key":"sQWomhH0pV"}],"key":"vpKz3JcbEq"},{"type":"text","value":":  Perform large computations by performing many smaller computations.","position":{"start":{"line":7,"column":1},"end":{"line":7,"column":1}},"key":"XXyo3vU5zy"}],"key":"qSGMkaSuzE"}],"key":"YhzrAJCzWM"}],"key":"EdMjnoUtXm"},{"type":"block","kind":"notebook-content","children":[{"type":"image","style":{"marginLeft":"10px"},"url":"/build/037e4310c3913e72533173c453c9e52f.svg","key":"rt8PFG4iL6","urlSource":"https://docs.dask.org/en/stable/_images/dask-array.svg"},{"type":"paragraph","position":{"start":{"line":4,"column":1},"end":{"line":4,"column":1}},"children":[{"type":"text","value":"In other words, Dask Array implements a subset of the NumPy ndarray interface using blocked algorithms, cutting up the large array into many small arrays. This lets us compute on arrays larger than memory using all of our cores. We coordinate these blocked algorithms using Dask graphs.","position":{"start":{"line":4,"column":1},"end":{"line":4,"column":1}},"key":"ygVwxsqlFG"}],"key":"jDZSUApCpF"},{"type":"paragraph","position":{"start":{"line":6,"column":1},"end":{"line":7,"column":1}},"children":[{"type":"text","value":"In this notebook, we’ll build some understanding by implementing some blocked algorithms from scratch.\nWe’ll then use Dask Array to analyze large datasets, in parallel, using a familiar NumPy-like API.","position":{"start":{"line":6,"column":1},"end":{"line":6,"column":1}},"key":"D2sYNlntzL"}],"key":"yPokGzW8gy"},{"type":"paragraph","position":{"start":{"line":9,"column":1},"end":{"line":9,"column":1}},"children":[{"type":"strong","position":{"start":{"line":9,"column":1},"end":{"line":9,"column":1}},"children":[{"type":"text","value":"Related Documentation","position":{"start":{"line":9,"column":1},"end":{"line":9,"column":1}},"key":"vsA3buVJAA"}],"key":"Pp7TgQp3Hk"}],"key":"GV746IkvuT"},{"type":"list","ordered":false,"spread":false,"position":{"start":{"line":11,"column":1},"end":{"line":14,"column":1}},"children":[{"type":"listItem","spread":true,"position":{"start":{"line":11,"column":1},"end":{"line":11,"column":1}},"children":[{"type":"link","url":"https://docs.dask.org/en/latest/array.html","position":{"start":{"line":11,"column":1},"end":{"line":11,"column":1}},"children":[{"type":"text","value":"Array documentation","position":{"start":{"line":11,"column":1},"end":{"line":11,"column":1}},"key":"LxCxsTXimV"}],"urlSource":"https://docs.dask.org/en/latest/array.html","key":"QfoQSmWvve"}],"key":"tYrVciYDgh"},{"type":"listItem","spread":true,"position":{"start":{"line":12,"column":1},"end":{"line":12,"column":1}},"children":[{"type":"link","url":"https://youtu.be/9h_61hXCDuI","position":{"start":{"line":12,"column":1},"end":{"line":12,"column":1}},"children":[{"type":"text","value":"Array screencast","position":{"start":{"line":12,"column":1},"end":{"line":12,"column":1}},"key":"OFBVY1lRZ7"}],"urlSource":"https://youtu.be/9h_61hXCDuI","key":"t4nFhiaD2B"}],"key":"BKZ8tJ1Bvt"},{"type":"listItem","spread":true,"position":{"start":{"line":13,"column":1},"end":{"line":13,"column":1}},"children":[{"type":"link","url":"https://docs.dask.org/en/latest/array-api.html","position":{"start":{"line":13,"column":1},"end":{"line":13,"column":1}},"children":[{"type":"text","value":"Array API","position":{"start":{"line":13,"column":1},"end":{"line":13,"column":1}},"key":"tmAKqtze4M"}],"urlSource":"https://docs.dask.org/en/latest/array-api.html","key":"cC0tFcCYXY"}],"key":"rrrrtkzXsv"},{"type":"listItem","spread":true,"position":{"start":{"line":14,"column":1},"end":{"line":14,"column":1}},"children":[{"type":"link","url":"https://examples.dask.org/array.html","position":{"start":{"line":14,"column":1},"end":{"line":14,"column":1}},"children":[{"type":"text","value":"Array examples","position":{"start":{"line":14,"column":1},"end":{"line":14,"column":1}},"key":"kZBiGrYvpx"}],"urlSource":"https://examples.dask.org/array.html","key":"m3sE669HgQ"}],"key":"sscw2MMVee"}],"key":"EHApIHGiQC"}],"key":"vuCmWEQLX5"},{"type":"block","kind":"notebook-content","children":[{"type":"heading","depth":4,"position":{"start":{"line":1,"column":1},"end":{"line":1,"column":1}},"children":[{"type":"text","value":"Arrays - Example","position":{"start":{"line":1,"column":1},"end":{"line":1,"column":1}},"key":"SGysGG1HsF"}],"identifier":"arrays-example","label":"Arrays - Example","html_id":"arrays-example","implicit":true,"key":"EXUOFgiMlF"}],"key":"B0GsPhwAgq"},{"type":"block","kind":"notebook-content","children":[{"type":"paragraph","position":{"start":{"line":1,"column":1},"end":{"line":1,"column":1}},"children":[{"type":"text","value":"A dask array looks and feels a lot like a numpy array. However, a dask array doesn’t directly hold any data. Instead, it symbolically represents the computations needed to generate the data. Nothing is actually computed until the actual numerical values are needed. This mode of operation is called “lazy”; it allows one to build up complex, large calculations symbolically before turning them over the scheduler for execution.","position":{"start":{"line":1,"column":1},"end":{"line":1,"column":1}},"key":"ABGNYIEgqd"}],"key":"ckyuoJJmam"}],"key":"opK8kleKOl"},{"type":"block","kind":"notebook-content","children":[{"type":"paragraph","position":{"start":{"line":1,"column":1},"end":{"line":1,"column":1}},"children":[{"type":"text","value":"If we want to create a numpy array of all ones, we do it like this:","position":{"start":{"line":1,"column":1},"end":{"line":1,"column":1}},"key":"A9k2whoxIQ"}],"key":"v9x3R3a0zv"}],"key":"Q1I2n5OcG0"},{"type":"block","kind":"notebook-code","children":[{"type":"code","lang":"python","executable":true,"value":"import numpy as np\nshape = (1000, 4000)\nones_np = np.ones(shape)\nones_np","key":"abSE9jwZqO"},{"type":"output","id":"q3CY8DUJWKOHaibKrp5yr","data":[],"key":"oPvBfTr2qt"}],"key":"Z8AapJ9rga"},{"type":"block","kind":"notebook-content","children":[{"type":"paragraph","position":{"start":{"line":1,"column":1},"end":{"line":1,"column":1}},"children":[{"type":"text","value":"This array contains exactly 32 MB of data:","position":{"start":{"line":1,"column":1},"end":{"line":1,"column":1}},"key":"HcAtHBr4Mm"}],"key":"H10xAfpYIN"}],"key":"RJHQGh8LY2"},{"type":"block","kind":"notebook-code","children":[{"type":"code","lang":"python","executable":true,"value":"print('%.1f MB' % (ones_np.nbytes / 1e6))","key":"B6IHUnjHmQ"},{"type":"output","id":"ZGayfim55kEEKM3L0230j","data":[],"key":"k6fiv7qQiT"}],"key":"lTD5u9QSIw"},{"type":"block","kind":"notebook-content","children":[{"type":"paragraph","position":{"start":{"line":1,"column":1},"end":{"line":1,"column":1}},"children":[{"type":"text","value":"Now let’s create the same array using dask’s array interface.","position":{"start":{"line":1,"column":1},"end":{"line":1,"column":1}},"key":"qDhsfB3Kh4"}],"key":"vuHF3dqFU0"}],"key":"vy9NBun2v7"},{"type":"block","kind":"notebook-code","children":[{"type":"code","lang":"python","executable":true,"value":"import dask.array as da\nones = da.ones(shape)\nones","key":"Qq9yXnfA6J"},{"type":"output","id":"nExgaBTHYbTp0DwljS8Zm","data":[],"key":"MIOj2pPwkZ"}],"key":"NJ4VOIhgNG"},{"type":"block","kind":"notebook-content","children":[{"type":"paragraph","position":{"start":{"line":1,"column":1},"end":{"line":1,"column":1}},"children":[{"type":"text","value":"This works, but we didn’t tell Dask how to split up the array, so it is not optimized for distributed computation.","position":{"start":{"line":1,"column":1},"end":{"line":1,"column":1}},"key":"MCV6TF7k09"}],"key":"xyVWgjjpXZ"},{"type":"paragraph","position":{"start":{"line":3,"column":1},"end":{"line":3,"column":1}},"children":[{"type":"text","value":"A crucial difference with Dask is that we must specify the chunks argument. “Chunks” describes how the array is split up over many sub-arrays.","position":{"start":{"line":3,"column":1},"end":{"line":3,"column":1}},"key":"VkU25sgpBk"}],"key":"EAKx0Yc3yf"},{"type":"paragraph","position":{"start":{"line":5,"column":1},"end":{"line":5,"column":1}},"children":[{"type":"text","value":"There are several ways to ","position":{"start":{"line":5,"column":1},"end":{"line":5,"column":1}},"key":"As3yooZ5oW"},{"type":"link","url":"https://docs.dask.org/en/stable/array-chunks.html","position":{"start":{"line":5,"column":1},"end":{"line":5,"column":1}},"children":[{"type":"text","value":"specify chunks","position":{"start":{"line":5,"column":1},"end":{"line":5,"column":1}},"key":"ykEKyXR57l"}],"urlSource":"https://docs.dask.org/en/stable/array-chunks.html","key":"JIJxiLTbk8"},{"type":"text","value":".","position":{"start":{"line":5,"column":1},"end":{"line":5,"column":1}},"key":"BEjvLzqCI7"}],"key":"LbLrQeo1e7"}],"key":"CZKUaa06ri"},{"type":"block","kind":"notebook-code","children":[{"type":"code","lang":"python","executable":true,"value":"chunk_shape = (1000, 1000)\nones = da.ones(shape, chunks=chunk_shape)\nones","key":"gMNyQiRByR"},{"type":"output","id":"IHe1HMCi5wKzXJjA8_IUQ","data":[],"key":"XvILGofgCA"}],"key":"nDeigsemuu"},{"type":"block","kind":"notebook-content","children":[{"type":"paragraph","position":{"start":{"line":1,"column":1},"end":{"line":1,"column":1}},"children":[{"type":"text","value":"Notice that we just see a symbolic representation of the array, including its shape, dtype, and chunksize. No data has been generated yet. When we call ","position":{"start":{"line":1,"column":1},"end":{"line":1,"column":1}},"key":"LLTwA5pwkQ"},{"type":"strong","position":{"start":{"line":1,"column":1},"end":{"line":1,"column":1}},"children":[{"type":"text","value":".compute()","position":{"start":{"line":1,"column":1},"end":{"line":1,"column":1}},"key":"lc0IZLg7s2"}],"key":"I8dYCh9WeB"},{"type":"text","value":" on a dask array, the computation is trigger and the dask array becomes a numpy array.","position":{"start":{"line":1,"column":1},"end":{"line":1,"column":1}},"key":"IKaXrmbCCJ"}],"key":"Svcw5YHGXN"}],"key":"hGq50KlD6Z"},{"type":"block","kind":"notebook-code","children":[{"type":"code","lang":"python","executable":true,"value":"ones.compute()","key":"q6cBitgAdz"},{"type":"output","id":"uQjGvMeC_ONq92iXN_UMe","data":[],"key":"BvRqmrv8yf"}],"key":"YpKxVHOVT0"},{"type":"block","kind":"notebook-content","children":[{"type":"paragraph","position":{"start":{"line":1,"column":1},"end":{"line":1,"column":1}},"children":[{"type":"text","value":"In order to understand what happened when we called .compute(), we can visualize the ","position":{"start":{"line":1,"column":1},"end":{"line":1,"column":1}},"key":"xT10OUuNIS"},{"type":"strong","position":{"start":{"line":1,"column":1},"end":{"line":1,"column":1}},"children":[{"type":"text","value":"Dask graph","position":{"start":{"line":1,"column":1},"end":{"line":1,"column":1}},"key":"lWkaRKZBBr"}],"key":"frIh6imbV8"},{"type":"text","value":", the symbolic operations, that make up the array.","position":{"start":{"line":1,"column":1},"end":{"line":1,"column":1}},"key":"qNXp4zwGI6"}],"key":"UlNJR8WE5Y"}],"key":"Irv6OSkk8x"},{"type":"block","kind":"notebook-code","children":[{"type":"code","lang":"python","executable":true,"value":"ones.visualize(format='svg')","key":"xUaut3oJ18"},{"type":"output","id":"8Dzj4DewnvxzVuG9v85_W","data":[],"key":"Dxo3mk2Xo2"}],"key":"txG5G716xz"},{"type":"block","kind":"notebook-content","children":[{"type":"paragraph","position":{"start":{"line":1,"column":1},"end":{"line":1,"column":1}},"children":[{"type":"text","value":"The array has four chunks. To generate it, Dask calls np.ones four times and then concatenates this together into one array.","position":{"start":{"line":1,"column":1},"end":{"line":1,"column":1}},"key":"syFEowXB9G"}],"key":"Xhcyin6gRO"},{"type":"paragraph","position":{"start":{"line":3,"column":1},"end":{"line":3,"column":1}},"children":[{"type":"text","value":"Rather than immediately loading a Dask array (which puts all the data into RAM), it is more common to reduce the data somehow. For example:","position":{"start":{"line":3,"column":1},"end":{"line":3,"column":1}},"key":"jUKVv2T6MR"}],"key":"doZuV0xxod"}],"key":"qBMiGvRqB5"},{"type":"block","kind":"notebook-code","children":[{"type":"code","lang":"python","executable":true,"value":"sum_of_ones = ones.sum()\nsum_of_ones.visualize(format='svg')","key":"rjl6IKcH0N"},{"type":"output","id":"K7aBiiEaUW_TGd9jyUOLs","data":[],"key":"aYDewfVlvw"}],"key":"h2WU5HZZEt"},{"type":"block","kind":"notebook-content","children":[{"type":"paragraph","position":{"start":{"line":1,"column":1},"end":{"line":1,"column":1}},"children":[{"type":"text","value":"Here we see Dask’s strategy for finding the sum. This simple example illustrates the beauty of Dask: it automatically designs an algorithm appropriate for custom operations with big data.","position":{"start":{"line":1,"column":1},"end":{"line":1,"column":1}},"key":"VWGx4jaWrf"}],"key":"k28j0tzVu9"},{"type":"paragraph","position":{"start":{"line":3,"column":1},"end":{"line":3,"column":1}},"children":[{"type":"text","value":"If we make our operation more complex, the graph gets more complex.","position":{"start":{"line":3,"column":1},"end":{"line":3,"column":1}},"key":"f7iBraF9DO"}],"key":"OyZQminbmr"}],"key":"TmmsUsv800"},{"type":"block","kind":"notebook-code","children":[{"type":"code","lang":"python","executable":true,"value":"fancy_calculation = (ones * ones[::-1, ::-1]).mean()\nfancy_calculation.visualize(format='svg')","key":"r6kqRNmaOq"},{"type":"output","id":"dmi65XXl_iNOTc_asgzjD","data":[],"key":"mP1hNAFlaS"}],"key":"nH0i1yeir0"},{"type":"block","kind":"notebook-content","children":[{"type":"heading","depth":3,"position":{"start":{"line":1,"column":1},"end":{"line":1,"column":1}},"children":[{"type":"text","value":"dask.delayed - parallelize generic Python code","position":{"start":{"line":1,"column":1},"end":{"line":1,"column":1}},"key":"zsyQwKj25r"}],"identifier":"dask-delayed-parallelize-generic-python-code","label":"dask.delayed - parallelize generic Python code","html_id":"dask-delayed-parallelize-generic-python-code","implicit":true,"key":"wAOXrjzczT"},{"type":"paragraph","position":{"start":{"line":2,"column":1},"end":{"line":2,"column":1}},"children":[{"type":"text","value":"What if you don’t have an Dask array or Dask dataframe? Instead of having blocks where the function is applied to each block, you can decorate functions with ","position":{"start":{"line":2,"column":1},"end":{"line":2,"column":1}},"key":"OzqjA23TEh"},{"type":"inlineCode","value":"@delayed","position":{"start":{"line":2,"column":1},"end":{"line":2,"column":1}},"key":"qeLyJpXYTe"},{"type":"text","value":" and ","position":{"start":{"line":2,"column":1},"end":{"line":2,"column":1}},"key":"Rqm3Z9PvAi"},{"type":"emphasis","position":{"start":{"line":2,"column":1},"end":{"line":2,"column":1}},"children":[{"type":"text","value":"have the functions themselves be lazy","position":{"start":{"line":2,"column":1},"end":{"line":2,"column":1}},"key":"IdUjzNTMtK"}],"key":"Ud857rJKP8"},{"type":"text","value":". Rather than compute its result immediately, it records what needs to be computed as a task into a graph that we’ll run later on parallel hardware.","position":{"start":{"line":2,"column":1},"end":{"line":2,"column":1}},"key":"iZ1Mm8OuVA"}],"key":"gH8cGAH4v1"},{"type":"paragraph","position":{"start":{"line":4,"column":1},"end":{"line":4,"column":1}},"children":[{"type":"text","value":"This is a simple way to use Dask to parallelize existing codebases or build ","position":{"start":{"line":4,"column":1},"end":{"line":4,"column":1}},"key":"HTsgsiFSCf"},{"type":"link","url":"https://blog.dask.org/2018/02/09/credit-models-with-dask","position":{"start":{"line":4,"column":1},"end":{"line":4,"column":1}},"children":[{"type":"text","value":"complex systems","position":{"start":{"line":4,"column":1},"end":{"line":4,"column":1}},"key":"Kn2zwKszbN"}],"urlSource":"https://blog.dask.org/2018/02/09/credit-models-with-dask","key":"ikqhuuOGaV"},{"type":"text","value":".","position":{"start":{"line":4,"column":1},"end":{"line":4,"column":1}},"key":"o0zaeLyXVu"}],"key":"M8Lt8MPdcj"},{"type":"paragraph","position":{"start":{"line":6,"column":1},"end":{"line":6,"column":1}},"children":[{"type":"strong","position":{"start":{"line":6,"column":1},"end":{"line":6,"column":1}},"children":[{"type":"text","value":"Related Documentation","position":{"start":{"line":6,"column":1},"end":{"line":6,"column":1}},"key":"Qce2ehdrDv"}],"key":"H7gLB0Bi6P"}],"key":"K8yoc5s652"},{"type":"list","ordered":false,"spread":false,"position":{"start":{"line":8,"column":1},"end":{"line":12,"column":1}},"children":[{"type":"listItem","spread":true,"position":{"start":{"line":8,"column":1},"end":{"line":8,"column":1}},"children":[{"type":"link","url":"https://docs.dask.org/en/latest/delayed.html","position":{"start":{"line":8,"column":1},"end":{"line":8,"column":1}},"children":[{"type":"text","value":"Delayed documentation","position":{"start":{"line":8,"column":1},"end":{"line":8,"column":1}},"key":"AunEpEEVyp"}],"urlSource":"https://docs.dask.org/en/latest/delayed.html","key":"z6AwAlRTeG"}],"key":"kDtHsa8fGV"},{"type":"listItem","spread":true,"position":{"start":{"line":9,"column":1},"end":{"line":9,"column":1}},"children":[{"type":"link","url":"https://www.youtube.com/watch?v=SHqFmynRxVU","position":{"start":{"line":9,"column":1},"end":{"line":9,"column":1}},"children":[{"type":"text","value":"Delayed screencast","position":{"start":{"line":9,"column":1},"end":{"line":9,"column":1}},"key":"bW1eJ1qLqM"}],"urlSource":"https://www.youtube.com/watch?v=SHqFmynRxVU","key":"okwNI3tbp2"}],"key":"DNqRysrAxJ"},{"type":"listItem","spread":true,"position":{"start":{"line":10,"column":1},"end":{"line":10,"column":1}},"children":[{"type":"link","url":"https://docs.dask.org/en/latest/delayed-api.html","position":{"start":{"line":10,"column":1},"end":{"line":10,"column":1}},"children":[{"type":"text","value":"Delayed API","position":{"start":{"line":10,"column":1},"end":{"line":10,"column":1}},"key":"ClisF3wQ2u"}],"urlSource":"https://docs.dask.org/en/latest/delayed-api.html","key":"u37iMMO2BR"}],"key":"aYzgJ3gvpU"},{"type":"listItem","spread":true,"position":{"start":{"line":11,"column":1},"end":{"line":11,"column":1}},"children":[{"type":"link","url":"https://examples.dask.org/delayed.html","position":{"start":{"line":11,"column":1},"end":{"line":11,"column":1}},"children":[{"type":"text","value":"Delayed examples","position":{"start":{"line":11,"column":1},"end":{"line":11,"column":1}},"key":"zE3CvGm9D1"}],"urlSource":"https://examples.dask.org/delayed.html","key":"pcF1dBfHHZ"}],"key":"ou6DyGj6F1"},{"type":"listItem","spread":true,"position":{"start":{"line":12,"column":1},"end":{"line":12,"column":1}},"children":[{"type":"link","url":"https://docs.dask.org/en/latest/delayed-best-practices.html","position":{"start":{"line":12,"column":1},"end":{"line":12,"column":1}},"children":[{"type":"text","value":"Delayed best practices","position":{"start":{"line":12,"column":1},"end":{"line":12,"column":1}},"key":"yZvmnSbm20"}],"urlSource":"https://docs.dask.org/en/latest/delayed-best-practices.html","key":"mSkb4pHPQB"}],"key":"Vb26SXQ4kU"}],"key":"DfkYpj0pXU"}],"key":"irRLDOzeN3"},{"type":"block","kind":"notebook-content","children":[{"type":"paragraph","position":{"start":{"line":1,"column":1},"end":{"line":2,"column":1}},"children":[{"type":"text","value":"A typical workfow Read-Transform-Write workflow are most often implemented as outlined hereafter.\nIn general, most workflows containing a for-loop can benefit from dask.delayed.","position":{"start":{"line":1,"column":1},"end":{"line":1,"column":1}},"key":"vYyqcmgBgW"}],"key":"w8xt0ehj8s"},{"type":"code","lang":"python","value":"import dask\n    \n@dask.delayed\ndef process_file(filename):\n    data = read_a_file(filename)\n    data = do_a_transformation(data)\n    destination = f\"results/{filename}\"\n    write_out_data(data, destination)\n    return destination\n\nresults = []\nfor filename in filenames:\n    results.append(process_file(filename))\n    \ndask.compute(results)","position":{"start":{"line":3,"column":1},"end":{"line":19,"column":1}},"key":"svKJcZSckk"}],"key":"PtJPR9823w"},{"type":"block","kind":"notebook-content","children":[{"type":"heading","depth":5,"position":{"start":{"line":1,"column":1},"end":{"line":1,"column":1}},"children":[{"type":"text","value":"dask.delayed - Example","position":{"start":{"line":1,"column":1},"end":{"line":1,"column":1}},"key":"kEP2KCBQnM"}],"identifier":"dask-delayed-example","label":"dask.delayed - Example","html_id":"dask-delayed-example","implicit":true,"key":"n0IPi7btwf"},{"type":"paragraph","position":{"start":{"line":2,"column":1},"end":{"line":2,"column":1}},"children":[{"type":"text","value":"For demonstration purposes we will create simple functions to perform simple operations like add two numbers together, but they sleep for a random amount of time to simulate real work.","position":{"start":{"line":2,"column":1},"end":{"line":2,"column":1}},"key":"ncTdMsLtPd"}],"key":"TaRjAYNxoH"}],"key":"wdiQ3z1ws7"},{"type":"block","kind":"notebook-code","children":[{"type":"code","lang":"python","executable":true,"value":"import time\n\ndef inc(x):\n    time.sleep(0.1)\n    return x + 1\n\ndef dec(x):\n    time.sleep(0.1)\n    return x - 1\n\ndef add(x, y):\n    time.sleep(0.2)\n    return x + y","key":"pKouOMcopI"},{"type":"output","id":"o8arWYOiGsZ4j5YDdF2_3","data":[],"key":"CyHzIYAeA4"}],"key":"GrgMYTeEPP"},{"type":"block","kind":"notebook-content","children":[{"type":"paragraph","position":{"start":{"line":1,"column":1},"end":{"line":1,"column":1}},"children":[{"type":"text","value":"We can run them like normal Python functions below","position":{"start":{"line":1,"column":1},"end":{"line":1,"column":1}},"key":"dxSS09TBAz"}],"key":"dHpk12yBVQ"}],"key":"ttA39wDUWb"},{"type":"block","kind":"notebook-code","children":[{"type":"code","lang":"python","executable":true,"value":"%%time\nx = inc(1)\ny = dec(2)\nz = add(x, y)\nz","key":"XWAdYdE46j"},{"type":"output","id":"lbRX0HoYUB9xWu8Aj1zY1","data":[],"key":"JFPsRCSfnX"}],"key":"ioAf95RWY6"},{"type":"block","kind":"notebook-content","children":[{"type":"paragraph","position":{"start":{"line":1,"column":1},"end":{"line":1,"column":1}},"children":[{"type":"text","value":"These ran one after the other, in sequence. Note though that the first two lines inc(1) and dec(2) don’t depend on each other, we could have called them in parallel.","position":{"start":{"line":1,"column":1},"end":{"line":1,"column":1}},"key":"fD7EDUF1NJ"}],"key":"vbgSnLBh7C"},{"type":"paragraph","position":{"start":{"line":3,"column":1},"end":{"line":3,"column":1}},"children":[{"type":"text","value":"We can call dask.delayed on these funtions to make them lazy. Rather than compute their results immediately, they record what we want to compute as a task into a graph that we’ll run later on parallel hardware.","position":{"start":{"line":3,"column":1},"end":{"line":3,"column":1}},"key":"T2mWa18EA4"}],"key":"aoAx3JtcYN"}],"key":"XtmtabLAbK"},{"type":"block","kind":"notebook-code","children":[{"type":"code","lang":"python","executable":true,"value":"import dask\ninc = dask.delayed(inc)\ndec = dask.delayed(dec)\nadd = dask.delayed(add)","key":"HZemd7OBd5"},{"type":"output","id":"DJB_kZkOgFwDzjMkQ2VxU","data":[],"key":"tAsVmTpaF2"}],"key":"gXxcEhiZ02"},{"type":"block","kind":"notebook-content","children":[{"type":"paragraph","position":{"start":{"line":1,"column":1},"end":{"line":1,"column":1}},"children":[{"type":"text","value":"Calling these lazy functions is now almost free. We’re just constructing a graph","position":{"start":{"line":1,"column":1},"end":{"line":1,"column":1}},"key":"kFWRLDfHlo"}],"key":"SswF793dVu"}],"key":"J0sE88smKi"},{"type":"block","kind":"notebook-code","children":[{"type":"code","lang":"python","executable":true,"value":"%%time\nx = inc(1)\ny = dec(2)\nz = add(x, y)\nz","key":"EziBkhJO6J"},{"type":"output","id":"pzXaYcATWUmc989vDjR-_","data":[],"key":"tTGwcBXCL1"}],"key":"viqcPFZIEf"},{"type":"block","kind":"notebook-content","children":[{"type":"paragraph","position":{"start":{"line":1,"column":1},"end":{"line":1,"column":1}},"children":[{"type":"text","value":"Visualize computation","position":{"start":{"line":1,"column":1},"end":{"line":1,"column":1}},"key":"jWRGXq09pU"}],"key":"T5fqiSyMMm"}],"key":"NsX991puHW"},{"type":"block","kind":"notebook-code","children":[{"type":"code","lang":"python","executable":true,"value":"z.visualize(format='svg', rankdir='LR')","key":"VNDPVIpdDp"},{"type":"output","id":"nMy6Hlg93tzGI17LN7p-2","data":[],"key":"KEjrvxaVlO"}],"key":"SPZQny2y6C"},{"type":"block","kind":"notebook-content","children":[{"type":"paragraph","position":{"start":{"line":1,"column":1},"end":{"line":1,"column":1}},"children":[{"type":"text","value":"Run in parallel. Call .compute() when you want your result as a normal Python object","position":{"start":{"line":1,"column":1},"end":{"line":1,"column":1}},"key":"ul8fNFdp23"}],"key":"mTna63D9EL"}],"key":"P7514IF0LS"},{"type":"block","kind":"notebook-code","children":[{"type":"code","lang":"python","executable":true,"value":"%%time\nz.compute()","key":"lRZERZPlNS"},{"type":"output","id":"HoYEpnNbCuFXbfrQFinbG","data":[],"key":"YMY7Je4XvE"}],"key":"MtJKDFWpeC"},{"type":"block","kind":"notebook-content","children":[{"type":"paragraph","position":{"start":{"line":1,"column":1},"end":{"line":1,"column":1}},"children":[{"type":"strong","position":{"start":{"line":1,"column":1},"end":{"line":1,"column":1}},"children":[{"type":"text","value":"Parallelize Normal Python code","position":{"start":{"line":1,"column":1},"end":{"line":1,"column":1}},"key":"WOGTnR4zKK"}],"key":"SLAwOw2afQ"}],"key":"sGYtpeTCEh"},{"type":"paragraph","position":{"start":{"line":3,"column":1},"end":{"line":3,"column":1}},"children":[{"type":"text","value":"Now we use dask.delayed in a normal for-loop Python code as given in the example above. This generates graphs instead of doing computations directly, but still looks like the code we had before. Dask is a convenient way to add parallelism to existing workflows.","position":{"start":{"line":3,"column":1},"end":{"line":3,"column":1}},"key":"pnXmLTKXTr"}],"key":"E5w6jyvUXZ"}],"key":"evGZEiuO2i"},{"type":"block","kind":"notebook-code","children":[{"type":"code","lang":"python","executable":true,"value":"%%time\nzs = []\nfor i in range(256):\n    x = inc(i)\n    y = dec(x)\n    z = add(x, y)\n    zs.append(z)\n\nzs = dask.persist(*zs)   # trigger computation in the background","key":"GiGUr2591x"},{"type":"output","id":"8ZNM7gS8IaxXIU39dMEWv","data":[],"key":"GJdasUKt3u"}],"key":"phqNAzcge2"},{"type":"block","kind":"notebook-content","children":[{"type":"heading","depth":2,"position":{"start":{"line":1,"column":1},"end":{"line":1,"column":1}},"children":[{"type":"text","value":"Dask Cluster (dask.distributed)","position":{"start":{"line":1,"column":1},"end":{"line":1,"column":1}},"key":"ueuzIcF50O"}],"identifier":"dask-cluster-dask-distributed","label":"Dask Cluster (dask.distributed)","html_id":"dask-cluster-dask-distributed","implicit":true,"key":"UEbYetrRRW"},{"type":"paragraph","position":{"start":{"line":2,"column":1},"end":{"line":3,"column":1}},"children":[{"type":"text","value":"Dask has the ability to run work on multiple machines using the distributed scheduler. ","position":{"start":{"line":2,"column":1},"end":{"line":2,"column":1}},"key":"y3KXDJQdi3"},{"type":"inlineCode","value":"dask.distributed","position":{"start":{"line":2,"column":1},"end":{"line":2,"column":1}},"key":"qlAP5eq9Sa"},{"type":"text","value":" is a lightweight library for distributed computing in Python. It extends both the ","position":{"start":{"line":2,"column":1},"end":{"line":2,"column":1}},"key":"ufZwO8BJ3z"},{"type":"inlineCode","value":"concurrent.futures","position":{"start":{"line":2,"column":1},"end":{"line":2,"column":1}},"key":"KEIBdx9Alt"},{"type":"text","value":" and Dask APIs to run on various clusters technologies such as Kubernetes, Yarn, SLURM, PBS, etc. .\nMost of the times when you are using Dask, you will be using a distributed scheduler, which exists in the context of a Dask cluster. When we talk about Dask Clusters we can think of those as depicted in the following:","position":{"start":{"line":2,"column":1},"end":{"line":2,"column":1}},"key":"cAgt8PDdtr"}],"key":"rUxDZLqy1A"},{"type":"paragraph","children":[{"type":"image","url":"/build/7445a9f1307deaa4760238b8ed4d85c3.png","alt":"Distributed overview","key":"McTL3Q872d","urlSource":"https://tutorial.dask.org/_images/distributed-overview.png"}],"key":"ookGV6oFBm"}],"key":"u5EWQBIIaP"},{"type":"block","kind":"notebook-content","children":[{"type":"heading","depth":2,"position":{"start":{"line":1,"column":1},"end":{"line":1,"column":1}},"children":[{"type":"text","value":"Dask @ DEDL","position":{"start":{"line":1,"column":1},"end":{"line":1,"column":1}},"key":"JuS3FXRC7G"}],"identifier":"dask-dedl","label":"Dask @ DEDL","html_id":"dask-dedl","implicit":true,"key":"GeBalErW3H"},{"type":"paragraph","position":{"start":{"line":2,"column":1},"end":{"line":2,"column":1}},"children":[{"type":"text","value":"DestinE Data Lake utilises a deployment of ","position":{"start":{"line":2,"column":1},"end":{"line":2,"column":1}},"key":"tjDz5jtRGQ"},{"type":"link","url":"https://gateway.dask.org/","position":{"start":{"line":2,"column":1},"end":{"line":2,"column":1}},"children":[{"type":"text","value":"Dask Gateway","position":{"start":{"line":2,"column":1},"end":{"line":2,"column":1}},"key":"pVyyx6PP4q"}],"urlSource":"https://gateway.dask.org/","key":"HmGbTWgqKp"},{"type":"text","value":" on each location (bridge) in the data lake. Dask Gateway provides a secure, multi-tenant server for managing Dask clusters. It allows users to launch and use Dask clusters in a shared, centrally managed cluster environment, without requiring users to have direct access to the underlying cluster backend (e.g. Kubernetes, Hadoop/YARN, HPC Job queues, etc…).","position":{"start":{"line":2,"column":1},"end":{"line":2,"column":1}},"key":"Ot9NYsAQD3"}],"key":"P88asPDRCS"},{"type":"paragraph","position":{"start":{"line":4,"column":1},"end":{"line":5,"column":1}},"children":[{"type":"text","value":"Dask Gateway exposes a REST API to spawn clusters on demand. The overall architecture of Dask Gateway is depicted hereafter.\n","position":{"start":{"line":4,"column":1},"end":{"line":4,"column":1}},"key":"k0J5p5hDho"},{"type":"image","url":"/build/04cc7514c92f1ae43e3b621d7cc0a124.svg","key":"pRQSBHz9A6","urlSource":"https://gateway.dask.org/_images/architecture.svg"}],"key":"UyScqKhkwZ"},{"type":"heading","depth":3,"position":{"start":{"line":7,"column":1},"end":{"line":7,"column":1}},"children":[{"type":"text","value":"How to connect and spawn a cluster?","position":{"start":{"line":7,"column":1},"end":{"line":7,"column":1}},"key":"i8vaiTYZqh"}],"identifier":"how-to-connect-and-spawn-a-cluster","label":"How to connect and spawn a cluster?","html_id":"how-to-connect-and-spawn-a-cluster","implicit":true,"key":"zDen0YgWpS"},{"type":"paragraph","position":{"start":{"line":9,"column":1},"end":{"line":9,"column":1}},"children":[{"type":"strong","position":{"start":{"line":9,"column":1},"end":{"line":9,"column":1}},"children":[{"type":"text","value":"Central Site","position":{"start":{"line":9,"column":1},"end":{"line":9,"column":1}},"key":"oiP2wQT1aV"}],"key":"SpxqUaVVnZ"}],"key":"sdD4nKBXzP"},{"type":"list","ordered":false,"spread":false,"position":{"start":{"line":10,"column":1},"end":{"line":12,"column":1}},"children":[{"type":"listItem","spread":true,"position":{"start":{"line":10,"column":1},"end":{"line":10,"column":1}},"children":[{"type":"text","value":"address: ","position":{"start":{"line":10,"column":1},"end":{"line":10,"column":1}},"key":"y9IFnFHUTP"},{"type":"link","url":"http://dask.central.data.destination-earth.eu","position":{"start":{"line":10,"column":1},"end":{"line":10,"column":1}},"children":[{"type":"text","value":"http://​dask​.central​.data​.destination​-earth​.eu","position":{"start":{"line":10,"column":1},"end":{"line":10,"column":1}},"key":"rrH7RY4UPh"}],"urlSource":"http://dask.central.data.destination-earth.eu","key":"jDskm6G9qM"}],"key":"TfTqaE1iC9"},{"type":"listItem","spread":true,"position":{"start":{"line":11,"column":1},"end":{"line":12,"column":1}},"children":[{"type":"text","value":"proxy_address: tcp://dask.central.data.destination-earth.eu:80","position":{"start":{"line":11,"column":1},"end":{"line":11,"column":1}},"key":"ChMA3EopUw"}],"key":"o9yKrmSVj2"}],"key":"uGl68NFiWk"},{"type":"paragraph","position":{"start":{"line":13,"column":1},"end":{"line":13,"column":1}},"children":[{"type":"strong","position":{"start":{"line":13,"column":1},"end":{"line":13,"column":1}},"children":[{"type":"text","value":"LUMI Bridge","position":{"start":{"line":13,"column":1},"end":{"line":13,"column":1}},"key":"RdMulwirwU"}],"key":"N20f2i4bDg"}],"key":"eVr9yjX0dY"},{"type":"list","ordered":false,"spread":false,"position":{"start":{"line":14,"column":1},"end":{"line":15,"column":1}},"children":[{"type":"listItem","spread":true,"position":{"start":{"line":14,"column":1},"end":{"line":14,"column":1}},"children":[{"type":"text","value":"address: ","position":{"start":{"line":14,"column":1},"end":{"line":14,"column":1}},"key":"Qs6A7P1IyZ"},{"type":"link","url":"http://dask.lumi.data.destination-earth.eu","position":{"start":{"line":14,"column":1},"end":{"line":14,"column":1}},"children":[{"type":"text","value":"http://​dask​.lumi​.data​.destination​-earth​.eu","position":{"start":{"line":14,"column":1},"end":{"line":14,"column":1}},"key":"BZSMfjqPwp"}],"urlSource":"http://dask.lumi.data.destination-earth.eu","key":"q5OnGHDJ1S"}],"key":"BOy92mG1TY"},{"type":"listItem","spread":true,"position":{"start":{"line":15,"column":1},"end":{"line":15,"column":1}},"children":[{"type":"text","value":"proxy_address: tcp://dask.lumi.data.destination-earth.eu:80","position":{"start":{"line":15,"column":1},"end":{"line":15,"column":1}},"key":"QRS6jRWVFL"}],"key":"LK4yoRcnP5"}],"key":"eoxPjSs1GG"}],"key":"zwKIXIzjh4"},{"type":"block","kind":"notebook-code","data":{"tags":[]},"children":[{"type":"code","lang":"python","executable":true,"value":"from dask_gateway.auth import GatewayAuth\nfrom getpass import getpass\nfrom destinelab import AuthHandler as DESP_AuthHandler\n\nclass DESPAuth(GatewayAuth):\n    def __init__(self, username: str):\n        self.auth_handler = DESP_AuthHandler(username, getpass(\"Please input your DESP password: \"))\n        self.access_token = self.auth_handler.get_token()\n    \n    def pre_request(self, _):\n        headers = {\"Authorization\": \"Bearer \" + self.access_token}\n        return headers, None","visibility":"show","key":"TYnoAFUVui"},{"type":"output","id":"Qsi6pxeXTasZiAE09HyXx","data":[],"visibility":"show","key":"XpUrMfwuCq"}],"visibility":"show","key":"rOXrwCuxWK"},{"type":"block","kind":"notebook-content","children":[{"type":"paragraph","position":{"start":{"line":1,"column":1},"end":{"line":1,"column":1}},"children":[{"type":"text","value":"Only authenticated access is granted to the DEDL STACK service Dask, therefore a helper class to authenticate a user against the DESP identity management system is implemented. The users password is directly handed over to the request object and is not permanently stored.","position":{"start":{"line":1,"column":1},"end":{"line":1,"column":1}},"key":"yqpxRnQ8Fw"}],"key":"rwlxZ7LTwY"},{"type":"paragraph","position":{"start":{"line":3,"column":1},"end":{"line":3,"column":1}},"children":[{"type":"text","value":"In the following, please enter your DESP username and password. Again, the password will only be saved for the duration of this user session and will be remove as soon as the notebook/kernel is closed.","position":{"start":{"line":3,"column":1},"end":{"line":3,"column":1}},"key":"RpifDlJ9TI"}],"key":"KcFppmBafH"}],"key":"eDneSpjCZJ"},{"type":"block","kind":"notebook-code","data":{"tags":[]},"children":[{"type":"code","lang":"python","executable":true,"value":"from rich.prompt import Prompt\nmyAuth = DESPAuth(username=Prompt.ask(prompt=\"Username\"))","visibility":"show","key":"yktWuanf2m"},{"type":"output","id":"uxMgt7DCeC6k_1rChBVKt","data":[],"visibility":"show","key":"HIZD7ig5QU"}],"visibility":"show","key":"u03e4w7XIn"},{"type":"block","kind":"notebook-code","data":{"tags":[]},"children":[{"type":"code","lang":"python","executable":true,"value":"from dask_gateway import Gateway\ngateway = Gateway(address=\"http://dask.central.data.destination-earth.eu\",\n                  proxy_address=\"tcp://dask.central.data.destination-earth.eu:80\",\n                  auth=myAuth)","visibility":"show","key":"JxXkJjK8U5"},{"type":"output","id":"9xF3wkEnKdtabnBv29fYK","data":[],"visibility":"show","key":"li8b2M2STg"}],"visibility":"show","key":"RaOU1AEoKj"},{"type":"block","kind":"notebook-content","children":[{"type":"paragraph","position":{"start":{"line":1,"column":1},"end":{"line":1,"column":1}},"children":[{"type":"text","value":"Cluster creation and client instantiation to communicate with the new cluster","position":{"start":{"line":1,"column":1},"end":{"line":1,"column":1}},"key":"JrPbUunlwY"}],"key":"UsXbBPfDv0"}],"key":"mj6fr0KBVv"},{"type":"block","kind":"notebook-code","data":{"tags":[]},"children":[{"type":"code","lang":"python","executable":true,"value":"cluster = gateway.new_cluster()\nclient = cluster.get_client()\ncluster","visibility":"show","key":"pfF8s2m756"},{"type":"output","id":"sxtisFSxwHdEONbs2Sypd","data":[],"visibility":"show","key":"SMjJZVAajd"}],"visibility":"show","key":"wUarBXpLHX"},{"type":"block","kind":"notebook-content","children":[{"type":"paragraph","position":{"start":{"line":1,"column":1},"end":{"line":1,"column":1}},"children":[{"type":"text","value":"Up to now the cluster will only consist of the distributed scheduler. If you want to spawn workers directly via Python adaptively, please use the following method call. With the following the cluster will be scaled to 2 workers initially. Depending on the load, Dask will add addtional workers, up to 5, if needed.","position":{"start":{"line":1,"column":1},"end":{"line":1,"column":1}},"key":"Z48dJos2nS"}],"key":"qsvPLRUb0j"}],"key":"yxDaupPdjc"},{"type":"block","kind":"notebook-code","data":{"tags":[]},"children":[{"type":"code","lang":"python","executable":true,"value":"cluster.adapt(minimum=2, maximum=5)","visibility":"show","key":"xTC1R5kwNa"},{"type":"output","id":"Wh8vzR2s1tVxL-udnqHcC","data":[],"visibility":"show","key":"B9WQNg4mIX"}],"visibility":"show","key":"SyVFI4PbE5"},{"type":"block","kind":"notebook-content","data":{"tags":[]},"children":[{"type":"heading","depth":4,"position":{"start":{"line":1,"column":1},"end":{"line":1,"column":1}},"children":[{"type":"text","value":"dask.futures - non-blocking distributed calculations","position":{"start":{"line":1,"column":1},"end":{"line":1,"column":1}},"key":"pu4eZ4xXHD"}],"identifier":"dask-futures-non-blocking-distributed-calculations","label":"dask.futures - non-blocking distributed calculations","html_id":"dask-futures-non-blocking-distributed-calculations","implicit":true,"key":"yKjgclcXCE"},{"type":"paragraph","position":{"start":{"line":2,"column":1},"end":{"line":2,"column":1}},"children":[{"type":"text","value":"We will now make use of the remote Dask Cluster using the Dask low-level collection dask.futures.","position":{"start":{"line":2,"column":1},"end":{"line":2,"column":1}},"key":"AJJkWWvp52"}],"key":"oQqTBLctv5"},{"type":"paragraph","position":{"start":{"line":4,"column":1},"end":{"line":4,"column":1}},"children":[{"type":"text","value":"Submit arbitrary functions for computation in a parallelized, eager, and non-blocking way.","position":{"start":{"line":4,"column":1},"end":{"line":4,"column":1}},"key":"EWOAEMAZje"}],"key":"KojYNkXplG"},{"type":"paragraph","position":{"start":{"line":6,"column":1},"end":{"line":6,"column":1}},"children":[{"type":"text","value":"The ","position":{"start":{"line":6,"column":1},"end":{"line":6,"column":1}},"key":"i769nHEGz9"},{"type":"inlineCode","value":"futures","position":{"start":{"line":6,"column":1},"end":{"line":6,"column":1}},"key":"WI13ZQAIfv"},{"type":"text","value":" interface (derived from the built-in ","position":{"start":{"line":6,"column":1},"end":{"line":6,"column":1}},"key":"deR5ia66MR"},{"type":"inlineCode","value":"concurrent.futures","position":{"start":{"line":6,"column":1},"end":{"line":6,"column":1}},"key":"RU8R99LEqo"},{"type":"text","value":") provide fine-grained real-time execution for custom situations. We can submit individual functions for evaluation with one set of inputs, or evaluated over a sequence of inputs with ","position":{"start":{"line":6,"column":1},"end":{"line":6,"column":1}},"key":"vbU7oLDgCJ"},{"type":"inlineCode","value":"submit()","position":{"start":{"line":6,"column":1},"end":{"line":6,"column":1}},"key":"qdDKKS5EUN"},{"type":"text","value":" and ","position":{"start":{"line":6,"column":1},"end":{"line":6,"column":1}},"key":"cktSkkDc4N"},{"type":"inlineCode","value":"map()","position":{"start":{"line":6,"column":1},"end":{"line":6,"column":1}},"key":"Twlb0pVfAk"},{"type":"text","value":". The call returns immediately, giving one or more ","position":{"start":{"line":6,"column":1},"end":{"line":6,"column":1}},"key":"nwg8nPcWsc"},{"type":"emphasis","position":{"start":{"line":6,"column":1},"end":{"line":6,"column":1}},"children":[{"type":"text","value":"futures","position":{"start":{"line":6,"column":1},"end":{"line":6,"column":1}},"key":"ybrnBuKnkm"}],"key":"KhiJBVG8nP"},{"type":"text","value":", whose status begins as “pending” and later becomes “finished”. There is no blocking of the local Python session.","position":{"start":{"line":6,"column":1},"end":{"line":6,"column":1}},"key":"mLnlK4IeMY"}],"key":"f8xcIFtqgf"},{"type":"paragraph","position":{"start":{"line":8,"column":1},"end":{"line":8,"column":1}},"children":[{"type":"strong","position":{"start":{"line":8,"column":1},"end":{"line":8,"column":1}},"children":[{"type":"text","value":"Important","position":{"start":{"line":8,"column":1},"end":{"line":8,"column":1}},"key":"YWRSYiHAzA"}],"key":"LonvDUSSnh"}],"key":"JRIKzVQRvh"},{"type":"paragraph","position":{"start":{"line":10,"column":1},"end":{"line":10,"column":1}},"children":[{"type":"text","value":"This is the important difference between futures and delayed. Both can be used to support arbitrary task scheduling, but delayed is lazy (it just constructs a graph) whereas futures are eager. With futures, as soon as the inputs are available and there is compute available, the computation starts.","position":{"start":{"line":10,"column":1},"end":{"line":10,"column":1}},"key":"ZLNdLsIVh7"}],"key":"vVbovqchra"},{"type":"paragraph","position":{"start":{"line":12,"column":1},"end":{"line":12,"column":1}},"children":[{"type":"strong","position":{"start":{"line":12,"column":1},"end":{"line":12,"column":1}},"children":[{"type":"text","value":"Related Documentation","position":{"start":{"line":12,"column":1},"end":{"line":12,"column":1}},"key":"bCBaJVS15w"}],"key":"ANEirmScZc"}],"key":"zXZgqBGBo6"},{"type":"list","ordered":false,"spread":false,"position":{"start":{"line":14,"column":1},"end":{"line":16,"column":1}},"children":[{"type":"listItem","spread":true,"position":{"start":{"line":14,"column":1},"end":{"line":14,"column":1}},"children":[{"type":"link","url":"https://docs.dask.org/en/latest/futures.html","position":{"start":{"line":14,"column":1},"end":{"line":14,"column":1}},"children":[{"type":"text","value":"Futures documentation","position":{"start":{"line":14,"column":1},"end":{"line":14,"column":1}},"key":"wsubWKrkyS"}],"urlSource":"https://docs.dask.org/en/latest/futures.html","key":"JxCloBRz0C"}],"key":"AJQesZfKf8"},{"type":"listItem","spread":true,"position":{"start":{"line":15,"column":1},"end":{"line":15,"column":1}},"children":[{"type":"link","url":"https://www.youtube.com/watch?v=07EiCpdhtDE","position":{"start":{"line":15,"column":1},"end":{"line":15,"column":1}},"children":[{"type":"text","value":"Futures screencast","position":{"start":{"line":15,"column":1},"end":{"line":15,"column":1}},"key":"hcUQH7eOfd"}],"urlSource":"https://www.youtube.com/watch?v=07EiCpdhtDE","key":"pdfEs7f0i3"}],"key":"ahbZ2h0R0R"},{"type":"listItem","spread":true,"position":{"start":{"line":16,"column":1},"end":{"line":16,"column":1}},"children":[{"type":"link","url":"https://examples.dask.org/futures.html","position":{"start":{"line":16,"column":1},"end":{"line":16,"column":1}},"children":[{"type":"text","value":"Futures examples","position":{"start":{"line":16,"column":1},"end":{"line":16,"column":1}},"key":"QSPk0G9m05"}],"urlSource":"https://examples.dask.org/futures.html","key":"twP8hBEjAB"}],"key":"yEWnfGuaFa"}],"key":"hScyuSUmKZ"}],"visibility":"show","key":"SJMcCku3IK"},{"type":"block","kind":"notebook-content","children":[{"type":"paragraph","position":{"start":{"line":1,"column":1},"end":{"line":1,"column":1}},"children":[{"type":"text","value":"This is the same workflow that as given above in the ","position":{"start":{"line":1,"column":1},"end":{"line":1,"column":1}},"key":"tHqnkq2YQW"},{"type":"inlineCode","value":"dask.delayed","position":{"start":{"line":1,"column":1},"end":{"line":1,"column":1}},"key":"h5SGJNWNtv"},{"type":"text","value":" section. It is a for-loop to iterate of certain files to perform a transformation and to write the result.","position":{"start":{"line":1,"column":1},"end":{"line":1,"column":1}},"key":"nt6TeYhDSW"}],"key":"SyofIE618S"},{"type":"code","lang":"python","value":"def process_file(filename):\n    data = read_a_file(filename)\n    data = do_a_transformation(data)\n    destination = f\"results/{filename}\"\n    write_out_data(data, destination)\n    return destination\n\nfutures = []\nfor filename in filenames:\n    future = client.submit(process_file, filename)\n    futures.append(future)\n    \nfutures","position":{"start":{"line":3,"column":1},"end":{"line":17,"column":1}},"key":"pUFW03EZxc"}],"key":"AZt4Fnq0vh"},{"type":"block","kind":"notebook-code","data":{"tags":[]},"children":[{"type":"code","lang":"python","executable":true,"value":"from time import sleep\n\n\ndef inc(x):\n    sleep(1)\n    return x + 1","visibility":"show","key":"H8msLeMuPA"},{"type":"output","id":"g2_ebTwY-wvBqJoEcfkrd","data":[],"visibility":"show","key":"QUZjeq7rrl"}],"visibility":"show","key":"Thu4Xbt5pQ"},{"type":"block","kind":"notebook-content","children":[{"type":"paragraph","position":{"start":{"line":1,"column":1},"end":{"line":1,"column":1}},"children":[{"type":"text","value":"We can run these function locally","position":{"start":{"line":1,"column":1},"end":{"line":1,"column":1}},"key":"JUIjGXhVBJ"}],"key":"sZ1mmDaqPm"}],"key":"vtN6StouWL"},{"type":"block","kind":"notebook-code","data":{"tags":[]},"children":[{"type":"code","lang":"python","executable":true,"value":"inc(1)","visibility":"show","key":"P99w9wtooU"},{"type":"output","id":"uGwzPflkBlUUCGwViIbb7","data":[],"visibility":"show","key":"GTdkxqp2I9"}],"visibility":"show","key":"YDTnKeTFf8"},{"type":"block","kind":"notebook-content","children":[{"type":"paragraph","position":{"start":{"line":1,"column":1},"end":{"line":1,"column":1}},"children":[{"type":"text","value":"Or we can submit them to run remotely with Dask. This immediately returns a future that points to the ongoing computation, and eventually to the stored result.","position":{"start":{"line":1,"column":1},"end":{"line":1,"column":1}},"key":"lfUwzWd1Yq"}],"key":"ktgKQdMLsS"}],"key":"nVXWSsngvm"},{"type":"block","kind":"notebook-code","data":{"tags":[]},"children":[{"type":"code","lang":"python","executable":true,"value":"future = client.submit(inc, 1)  # returns immediately with pending future\nfuture","visibility":"show","key":"uDLCaV9C3v"},{"type":"output","id":"J8sombjWxrWICkvX810H0","data":[],"visibility":"show","key":"JYcBfq34mv"}],"visibility":"show","key":"eywPbN2g2k"},{"type":"block","kind":"notebook-content","children":[{"type":"paragraph","position":{"start":{"line":1,"column":1},"end":{"line":1,"column":1}},"children":[{"type":"text","value":"If you wait a second, and then check on the future again, you’ll see that it has finished.","position":{"start":{"line":1,"column":1},"end":{"line":1,"column":1}},"key":"sw2CMMKYzB"}],"key":"rLPvZSPx2m"}],"key":"EuTSPWI2Q1"},{"type":"block","kind":"notebook-code","data":{"tags":[]},"children":[{"type":"code","lang":"python","executable":true,"value":"future","visibility":"show","key":"R3aHajw68k"},{"type":"output","id":"FJvzRg0naB-fcg8yIHM2K","data":[],"visibility":"show","key":"QDpeKX9xMA"}],"visibility":"show","key":"he4xbt2jpF"},{"type":"block","kind":"notebook-content","children":[{"type":"paragraph","position":{"start":{"line":1,"column":1},"end":{"line":1,"column":1}},"children":[{"type":"text","value":"You can block on the computation and gather the result with the .result() method.","position":{"start":{"line":1,"column":1},"end":{"line":1,"column":1}},"key":"XhkWHBxvh6"}],"key":"lzui6g2xTK"}],"key":"ilEU2CvARq"},{"type":"block","kind":"notebook-code","data":{"tags":[]},"children":[{"type":"code","lang":"python","executable":true,"value":"future.result()","visibility":"show","key":"gqQRdL1Qjm"},{"type":"output","id":"YJeL4LgTETqSnJPBJpJoG","data":[],"visibility":"show","key":"TplCgbQPHn"}],"visibility":"show","key":"wd5HMocJUe"},{"type":"block","kind":"notebook-content","children":[{"type":"paragraph","position":{"start":{"line":1,"column":1},"end":{"line":1,"column":1}},"children":[{"type":"strong","position":{"start":{"line":1,"column":1},"end":{"line":1,"column":1}},"children":[{"type":"text","value":"Other ways to wait for a future","position":{"start":{"line":1,"column":1},"end":{"line":1,"column":1}},"key":"y0CoR15R9z"}],"key":"YCfJJh4tML"}],"key":"QrivD8Jrfv"},{"type":"code","lang":"python","value":"from dask.distributed import wait, progress\nprogress(future)","position":{"start":{"line":2,"column":1},"end":{"line":5,"column":1}},"key":"rEin8zhz9X"},{"type":"paragraph","position":{"start":{"line":6,"column":1},"end":{"line":6,"column":1}},"children":[{"type":"text","value":"shows a progress bar in the notebook. This progress bar is also asynchronous, and doesn’t block the execution of other code in the meanwhile.","position":{"start":{"line":6,"column":1},"end":{"line":6,"column":1}},"key":"nKfyVJCYPj"}],"key":"HISvlO3Le9"},{"type":"code","lang":"python","value":"wait(future)","position":{"start":{"line":8,"column":1},"end":{"line":10,"column":1}},"key":"COMsmis7eZ"},{"type":"paragraph","position":{"start":{"line":11,"column":1},"end":{"line":11,"column":1}},"children":[{"type":"text","value":"blocks and forces the notebook to wait until the computation pointed to by ","position":{"start":{"line":11,"column":1},"end":{"line":11,"column":1}},"key":"RXhPtRF2tD"},{"type":"inlineCode","value":"future","position":{"start":{"line":11,"column":1},"end":{"line":11,"column":1}},"key":"O0tCCM7CPJ"},{"type":"text","value":" is done. However, note that if the result of ","position":{"start":{"line":11,"column":1},"end":{"line":11,"column":1}},"key":"ltMOmlCrWS"},{"type":"inlineCode","value":"inc()","position":{"start":{"line":11,"column":1},"end":{"line":11,"column":1}},"key":"FsRDULcFtI"},{"type":"text","value":" is sitting in the cluster, it would take ","position":{"start":{"line":11,"column":1},"end":{"line":11,"column":1}},"key":"ZO21Xc9IGU"},{"type":"strong","position":{"start":{"line":11,"column":1},"end":{"line":11,"column":1}},"children":[{"type":"text","value":"no time","position":{"start":{"line":11,"column":1},"end":{"line":11,"column":1}},"key":"GQIzdXFGMe"}],"key":"PjaClWvCVG"},{"type":"text","value":" to execute the computation now, because Dask notices that we are asking for the result of a computation it already knows about. More on this later.","position":{"start":{"line":11,"column":1},"end":{"line":11,"column":1}},"key":"ryo2hiToEQ"}],"key":"mXrzNVtFBg"},{"type":"paragraph","position":{"start":{"line":13,"column":1},"end":{"line":13,"column":1}},"children":[{"type":"strong","position":{"start":{"line":13,"column":1},"end":{"line":13,"column":1}},"children":[{"type":"text","value":"Other ways to gather results","position":{"start":{"line":13,"column":1},"end":{"line":13,"column":1}},"key":"jb4nPNzhjB"}],"key":"hpaX77CA5V"}],"key":"RWfBIhoW12"},{"type":"code","lang":"python","value":"client.gather(futures)","position":{"start":{"line":14,"column":1},"end":{"line":16,"column":1}},"key":"yxD9kRzUAp"},{"type":"paragraph","position":{"start":{"line":17,"column":1},"end":{"line":17,"column":1}},"children":[{"type":"text","value":"gathers results from more than one future.","position":{"start":{"line":17,"column":1},"end":{"line":17,"column":1}},"key":"oFZONHBMyq"}],"key":"xcnfQWXgMz"}],"key":"zADz6cWCxg"},{"type":"block","kind":"notebook-code","data":{"tags":[]},"children":[{"type":"code","lang":"python","executable":true,"value":"from dask.distributed import wait, progress\ndef inc(x):\n    sleep(1)\n    return x + 1\n\n\nfuture_x = client.submit(inc, 1)\nfuture_y = client.submit(inc, 2)\nfuture_z = client.submit(sum, [future_x, future_y])\nprogress(future_z)","visibility":"show","key":"lTSshCmmS8"},{"type":"output","id":"qjgdhF5cbmJ_mgxR81cxd","data":[],"visibility":"show","key":"RHp9lbvHPz"}],"visibility":"show","key":"hYdTG5QN9M"},{"type":"block","kind":"notebook-content","children":[{"type":"div","class":"alert-warning","children":[{"type":"text","value":"Remove your cluster again to free up resources when you are done.","key":"efptSEWe3k"}],"key":"bmOUnTSTzu"}],"key":"DT1OYO4Mxt"},{"type":"block","kind":"notebook-code","data":{"tags":[]},"children":[{"type":"code","lang":"python","executable":true,"value":"cluster.close(shutdown=True)","visibility":"show","key":"t14MZFgWgQ"},{"type":"output","id":"aFawSiWz68nPRFbxWixbn","data":[],"visibility":"show","key":"uwZQjUOxsR"}],"visibility":"show","key":"J16LZABXtw"}],"key":"u7g0hC8Lyl"},"references":{"cite":{"order":[],"data":{}}},"footer":{"navigation":{"prev":{"title":"STACK service - Python Client Dask","url":"/stack-python-client-dask","group":"STACK"},"next":{"title":"Data Cube populated with data obtained from Weather and Geophysical Extremes Digital Twin (DT) - ExtremeDT","url":"/extremedt-datacube","group":"STACK"}}},"domain":"http://localhost:3001"}